{
  "clients": [
    {
      "id": "1",
      "name": "Acme Corp",
      "status": "Active",
      "address": "123 Main St, NY",
      "description": "Primary enterprise client",
      "startDate": "2022-01-01",
      "endDate": "2025-12-31"
    },
    {
      "id": "2",
      "name": "Beta Solutions",
      "status": "Inactive",
      "address": "456 Market St, CA",
      "description": "Legacy system user",
      "startDate": "2020-06-15",
      "endDate": "2023-06-15"
    },
    {
      "id": "3",
      "name": "Gamma Enterprises",
      "status": "Active",
      "address": "789 Elm St, TX",
      "description": "Fast-growing tech client",
      "startDate": "2023-03-01",
      "endDate": "2026-03-01"
    },
    {
      "id": "4",
      "name": "Delta Services",
      "status": "Active",
      "address": "101 Ocean Dr, FL",
      "description": "Provides IT support",
      "startDate": "2021-09-01",
      "endDate": "2024-09-01"
    },
    {
      "id": "5",
      "name": "Epsilon Ltd",
      "status": "Inactive",
      "address": "500 Tech Ave, WA",
      "description": "Retail sector",
      "startDate": "2019-11-01",
      "endDate": "2022-11-01"
    },
    {
      "id": "6",
      "name": "Zeta Group",
      "status": "Active",
      "address": "600 Industrial Rd, NJ",
      "description": "Manufacturing client",
      "startDate": "2022-05-10",
      "endDate": "2025-05-10"
    },
    {
      "id": "7",
      "name": "Eta Dynamics",
      "status": "Inactive",
      "address": "700 Finance Blvd, IL",
      "description": "Finance operations",
      "startDate": "2020-01-01",
      "endDate": "2022-12-31"
    },
    {
      "id": "8",
      "name": "Theta Systems",
      "status": "Active",
      "address": "890 Silicon St, AZ",
      "description": "AI and automation",
      "startDate": "2023-07-01",
      "endDate": "2026-07-01"
    },
    {
      "id": "9",
      "name": "Iota Innovations",
      "status": "Active",
      "address": "900 Lab Rd, CO",
      "description": "Healthcare R&D",
      "startDate": "2021-04-15",
      "endDate": "2024-04-15"
    },
    {
      "id": "10",
      "name": "Kappa Tech",
      "status": "Inactive",
      "address": "321 Loop St, OH",
      "description": "SaaS provider",
      "startDate": "2018-08-01",
      "endDate": "2021-08-01"
    },
    {
      "id": "0b6d",
      "name": "Zora Corps",
      "description": "Automation Client",
      "address": "Down South , LA , India",
      "status": "Active",
      "startDate": "2025-08-06",
      "endDate": "2025-08-15"
    }
  ],
  "functionalAreas": [
    {
      "id": "1",
      "name": "Operations",
      "type": "Core",
      "definition": "Manages logistics and production",
      "startDate": "2023-01-01",
      "endDate": "2024-12-31",
      "alignClientId": 1
    },
    {
      "id": "2",
      "name": "Marketing",
      "type": "Support",
      "definition": "Handles promotions and branding",
      "startDate": "2022-05-10",
      "endDate": "2023-11-30",
      "alignClientId": 3
    },
    {
      "id": "3",
      "name": "Finance",
      "type": "Core",
      "definition": "Responsible for budgets and accounting",
      "startDate": "2022-06-01",
      "endDate": "2025-06-01",
      "alignClientId": 4
    },
    {
      "id": "4",
      "name": "HR",
      "type": "Support",
      "definition": "Human resources management",
      "startDate": "2023-03-15",
      "endDate": "2025-03-15",
      "alignClientId": 6
    },
    {
      "id": "5",
      "name": "IT Services",
      "type": "Technical",
      "definition": "Maintains IT infrastructure",
      "startDate": "2022-09-01",
      "endDate": "2024-09-01",
      "alignClientId": 8
    },
    {
      "id": "6",
      "name": "Research",
      "type": "Innovation",
      "definition": "Focuses on product R&D",
      "startDate": "2023-02-20",
      "endDate": "2025-02-20",
      "alignClientId": 9
    },
    {
      "id": "7",
      "name": "Customer Support",
      "type": "Support",
      "definition": "Handles customer issues and feedback",
      "startDate": "2023-04-01",
      "endDate": "2025-04-01",
      "alignClientId": 1
    },
    {
      "id": "8",
      "name": "Legal",
      "type": "Advisory",
      "definition": "Manages legal compliance",
      "startDate": "2022-01-01",
      "endDate": "2024-01-01",
      "alignClientId": 4
    },
    {
      "id": "9",
      "name": "Procurement",
      "type": "Operational",
      "definition": "Supplies and vendor management",
      "startDate": "2023-07-15",
      "endDate": "2026-07-15",
      "alignClientId": 6
    },
    {
      "id": "10",
      "name": "Analytics",
      "type": "Technical",
      "definition": "Data analysis and reporting",
      "startDate": "2022-10-01",
      "endDate": "2024-10-01",
      "alignClientId": 3
    }
  ],
  "roles": [
    {
      "id": "1",
      "name": "Admin",
      "type": "System",
      "definition": "Manages the platform",
      "startDate": "2022-01-01",
      "endDate": "2025-01-01",
      "status": "Active"
    },
    {
      "id": "2",
      "name": "Manager",
      "type": "Operational",
      "definition": "Oversees teams",
      "startDate": "2023-02-10",
      "endDate": "2026-02-10",
      "status": "Active"
    },
    {
      "id": "3",
      "name": "Developer",
      "type": "Technical",
      "definition": "Builds applications",
      "startDate": "2022-05-01",
      "endDate": "2024-05-01",
      "status": "Inactive"
    },
    {
      "id": "4",
      "name": "Designer",
      "type": "Creative",
      "definition": "Designs UI/UX",
      "startDate": "2023-01-20",
      "endDate": "2025-01-20",
      "status": "Active"
    },
    {
      "id": "5",
      "name": "Tester",
      "type": "QA",
      "definition": "Tests product features",
      "startDate": "2022-09-15",
      "endDate": "2024-09-15",
      "status": "Inactive"
    },
    {
      "id": "6",
      "name": "Analyst",
      "type": "Business",
      "definition": "Analyzes data trends",
      "startDate": "2023-06-01",
      "endDate": "2026-06-01",
      "status": "Active"
    },
    {
      "id": "7",
      "name": "Recruiter",
      "type": "HR",
      "definition": "Finds talent",
      "startDate": "2023-03-10",
      "endDate": "2025-03-10",
      "status": "Active"
    },
    {
      "id": "8",
      "name": "Consultant",
      "type": "External",
      "definition": "Advisory role",
      "startDate": "2022-11-01",
      "endDate": "2024-11-01",
      "status": "Inactive"
    },
    {
      "id": "9",
      "name": "Support Agent",
      "type": "Customer Service",
      "definition": "Handles support tickets",
      "startDate": "2022-10-01",
      "endDate": "2025-10-01",
      "status": "Active"
    },
    {
      "id": "10",
      "name": "Intern",
      "type": "Temporary",
      "definition": "Assists with tasks",
      "startDate": "2023-07-01",
      "endDate": "2023-12-31",
      "status": "Inactive"
    }
  ],
  "permissions": [
    {
      "id": "1",
      "name": "Read Reports",
      "definition": "Can view reports",
      "status": "Active",
      "clientId": 1,
      "permissionGroups": [
        "Reporting"
      ],
      "roleIds": [
        1,
        2
      ]
    },
    {
      "id": "2",
      "name": "Edit Users",
      "definition": "Can edit user details",
      "status": "Inactive",
      "clientId": 3,
      "permissionGroups": [
        "User Management"
      ],
      "roleIds": [
        1
      ]
    },
    {
      "id": "3",
      "name": "Manage Roles",
      "definition": "Can create/update roles",
      "status": "Active",
      "clientId": 4,
      "permissionGroups": [
        "Role Control"
      ],
      "roleIds": [
        1,
        6
      ]
    },
    {
      "id": "4",
      "name": "Access Analytics",
      "definition": "View dashboards and KPIs",
      "status": "Active",
      "clientId": 6,
      "permissionGroups": [
        "Analytics"
      ],
      "roleIds": [
        6,
        9
      ]
    },
    {
      "id": "5",
      "name": "Delete Data",
      "definition": "Can delete records",
      "status": "Inactive",
      "clientId": 8,
      "permissionGroups": [
        "Danger Zone"
      ],
      "roleIds": [
        1
      ]
    },
    {
      "id": "6",
      "name": "Approve Requests",
      "definition": "Can approve workflows",
      "status": "Active",
      "clientId": 9,
      "permissionGroups": [
        "Approvals"
      ],
      "roleIds": [
        2,
        4
      ]
    },
    {
      "id": "7",
      "name": "Manage Settings",
      "definition": "Access to app settings",
      "status": "Active",
      "clientId": 3,
      "permissionGroups": [
        "Settings"
      ],
      "roleIds": [
        1
      ]
    },
    {
      "id": "8",
      "name": "Create Campaigns",
      "definition": "Create marketing campaigns",
      "status": "Active",
      "clientId": 1,
      "permissionGroups": [
        "Marketing"
      ],
      "roleIds": [
        2,
        4
      ]
    },
    {
      "id": "9",
      "name": "Export Data",
      "definition": "Download platform data",
      "status": "Inactive",
      "clientId": 4,
      "permissionGroups": [
        "Export Tools"
      ],
      "roleIds": [
        6
      ]
    },
    {
      "id": "10",
      "name": "Read Logs",
      "definition": "Access system logs",
      "status": "Active",
      "clientId": 6,
      "permissionGroups": [
        "System Monitoring"
      ],
      "roleIds": [
        1,
        2,
        6
      ]
    }
  ]
}